_cercis_version.py
blackd/__init__.py
blackd/__main__.py
blackd/middlewares.py
blib2to3/Grammar.txt
blib2to3/LICENSE
blib2to3/PatternGrammar.txt
blib2to3/README
blib2to3/__init__.py
blib2to3/pygram.py
blib2to3/pytree.py
blib2to3/pgen2/__init__.py
blib2to3/pgen2/conv.py
blib2to3/pgen2/driver.py
blib2to3/pgen2/grammar.py
blib2to3/pgen2/literals.py
blib2to3/pgen2/parse.py
blib2to3/pgen2/pgen.py
blib2to3/pgen2/token.py
blib2to3/pgen2/tokenize.py
cercis/__init__.py
cercis/__main__.py
cercis/_width_table.py
cercis/brackets.py
cercis/cache.py
cercis/comments.py
cercis/concurrency.py
cercis/const.py
cercis/debug.py
cercis/files.py
cercis/handle_ipynb_magics.py
cercis/indent.py
cercis/linegen.py
cercis/lines.py
cercis/mode.py
cercis/nodes.py
cercis/numerics.py
cercis/output.py
cercis/parsing.py
cercis/py.typed
cercis/ranges.py
cercis/report.py
cercis/rusty.py
cercis/strings.py
cercis/trans.py
cercis/utils_line_wrapping.py
cercis/utils_linegen.py
cercis-0.2.5.dist-info/METADATA
cercis-0.2.5.dist-info/WHEEL
cercis-0.2.5.dist-info/entry_points.txt
cercis-0.2.5.dist-info/licenses/LICENSE
cercis-0.2.5.dist-info/licenses/LICENSE_ORIGINAL
cercis-0.2.5.dist-info/RECORD
